ties/__about__.py
ties/__init__.py
ties/__main__.py
ties/_configuration.py
ties/_consts.py
ties/_file_processing.py
ties/cli.py
ties/common_transforms.py
ties-0.0.0a9.dist-info/METADATA
ties-0.0.0a9.dist-info/WHEEL
ties-0.0.0a9.dist-info/entry_points.txt
ties-0.0.0a9.dist-info/licenses/LICENSE
ties-0.0.0a9.dist-info/RECORD
